leetquery/__init__.py
leetquery/__version__.py
leetquery/problem.py
leetquery/user.py
leetquery-0.2.5.dist-info/LICENSE
leetquery-0.2.5.dist-info/METADATA
leetquery-0.2.5.dist-info/WHEEL
leetquery-0.2.5.dist-info/top_level.txt
leetquery-0.2.5.dist-info/RECORD
