Metadata-Version: 2.1
Name: leetquery
Version: 0.2.5
Summary: Query and analyze data from leetcode
Home-page: https://github.com/ShuYuHuang/leetquery
Author: Shu-Yu Huang
Author-email: b123767195@gmail.com
License: MIT
Classifier: License :: OSI Approved :: MIT License
Classifier: Programming Language :: Python :: 3
Classifier: Operating System :: OS Independent
Requires-Python: >=3.7.0
License-File: LICENSE
Provides-Extra: test
Requires-Dist: pytest ; extra == 'test'
Requires-Dist: mock ; extra == 'test'
Requires-Dist: pre-commit ; extra == 'test'
Requires-Dist: black ==22.3.0 ; extra == 'test'
Requires-Dist: flake8 ==4.0.1 ; extra == 'test'
Requires-Dist: flake8-docstrings ==1.6.0 ; extra == 'test'
